<?xml version="1.0" encoding="UTF-8"?>
<objects serializationModel="Studio.02.03.00">
	<object class="AudioFile" id="{8ae53e2a-9318-4fc5-b4d9-a6cc53b81b0b}">
		<property name="assetPath">
			<value>2025-03-12 20-21-21.wav</value>
		</property>
		<property name="isStreaming">
			<value>true</value>
		</property>
		<property name="frequencyInKHz">
			<value>48</value>
		</property>
		<property name="channelCount">
			<value>2</value>
		</property>
		<property name="length">
			<value>41.237333333333332</value>
		</property>
		<relationship name="masterAssetFolder">
			<destination>{e96bc4b5-4558-4ce7-ba8b-256359a7616e}</destination>
		</relationship>
	</object>
</objects>
